build_package/__init__.py
build_package/__main__.py
build_package/say_hi.py
build_package_from_kadikoy-1.0.0.dist-info/LICENSE
build_package_from_kadikoy-1.0.0.dist-info/METADATA
build_package_from_kadikoy-1.0.0.dist-info/WHEEL
build_package_from_kadikoy-1.0.0.dist-info/entry_points.txt
build_package_from_kadikoy-1.0.0.dist-info/top_level.txt
build_package_from_kadikoy-1.0.0.dist-info/RECORD
