Metadata-Version: 2.1
Name: build-package-from-kadikoy
Version: 1.0.0
Summary: Just trying to build a new python package
Author-email: Murat Ergan <erganmurat.akt@gmail.com>
License: The MIT License (MIT)
Project-URL: Homepage, https://github.com
Keywords: just,trying,new,package
Classifier: License :: OSI Approved :: MIT License
Classifier: Programming Language :: Python
Classifier: Programming Language :: Python :: 3
Requires-Python: >=3.9
License-File: LICENSE
Provides-Extra: dev
